json_visitor/__init__.py
json_visitor/__main__.py
json_visitor/json_visitor.py
json_visitor/main.py
json_visitor/contextual_adapters/__init__.py
json_visitor/contextual_adapters/base_adapter.py
json_visitor/contextual_adapters/composite_adapter.py
json_visitor/contextual_adapters/inspector_adapter.py
json_visitor/scoping/__init__.py
json_visitor/scoping/list_item_scope.py
json_visitor/scoping/list_item_value_scope.py
json_visitor/scoping/list_scope.py
json_visitor/scoping/member_name_scope.py
json_visitor/scoping/member_scope.py
json_visitor/scoping/member_value_scope.py
json_visitor/scoping/object_scope.py
json_visitor/scoping/root_scope.py
json_visitor/scoping/scope.py
json_visitor/scoping/value_scope.py
json_visitor/simple_adapters/__init__.py
json_visitor/simple_adapters/base_adapter.py
json_visitor/simple_adapters/composite_adapter.py
json_visitor/simple_adapters/scope_adapter.py
json_visitor/simple_adapters/scope_inspector_adapter.py
json_visitor/subscription/__init__.py
json_visitor/subscription/contextual_subscription.py
json_visitor/subscription/simple_subscription.py
json_visitor/tokenizer/__init__.py
json_visitor/tokenizer/scope_walker.py
json_visitor/tokenizer/token_processor.py
json_visitor-1.0.0.dist-info/METADATA
json_visitor-1.0.0.dist-info/WHEEL
json_visitor-1.0.0.dist-info/top_level.txt
json_visitor-1.0.0.dist-info/RECORD
