Metadata-Version: 2.1
Name: json-visitor
Version: 1.0.0
Summary: Provides a Visitor pattern interface for iterating through a JSON file.
Home-page: https://github.com/FluxIX/PyJsonVisitor
Author: Chris Herrick
License: UNKNOWN
Project-URL: Bug Reports, https://github.com/FluxIX/PyJsonVisitor/issues
Project-URL: Source, https://github.com/FluxIX/PyJsonVisitor
Keywords: json,visitor,subscribe,subscription,subscriber
Platform: UNKNOWN
Classifier: Development Status :: 5 - Production/Stable
Classifier: Intended Audience :: Developers
Classifier: Topic :: Software Development :: Build Tools
Classifier: License :: OSI Approved :: MIT License
Classifier: Programming Language :: Python :: 3
Classifier: Programming Language :: Python :: 3.6
Classifier: Programming Language :: Python :: 3.7
Classifier: Programming Language :: Python :: 3.8
Classifier: Programming Language :: Python :: 3.9
Classifier: Programming Language :: Python :: 3.10
Classifier: Programming Language :: Python :: 3 :: Only
Requires-Python: >=3.6, <4
Requires-Dist: ijson
Requires-Dist: event-notifier
